memray/_memray.pyi
memray/_metadata.py
memray/__init__.pyi
memray/_version.py
memray/_errors.py
memray/_destination.py
memray/_memray_test_utils.pyx
memray/_inject.abi3.so
memray/__init__.py
memray/_memray.pyx
memray/_test.py
memray/_test_utils.cpython-313-darwin.so
memray/py.typed
memray/_memray.cpython-313-darwin.so
memray/_stats.py
memray/_thread_name_interceptor.py
memray/_stats.pyi
memray/_test_utils.pyi
memray/__main__.py
memray/.dylibs/liblz4.1.9.4.dylib
memray/_ipython/__init__.py
memray/_ipython/flamegraph.py
memray/commands/tree.py
memray/commands/run.py
memray/commands/attach.py
memray/commands/__init__.py
memray/commands/_attach.lldb
memray/commands/summary.py
memray/commands/common.py
memray/commands/stats.py
memray/commands/transform.py
memray/commands/live.py
memray/commands/flamegraph.py
memray/commands/table.py
memray/commands/parse.py
memray/commands/_attach.gdb
memray/reporters/tree.py
memray/reporters/frame_tools.py
memray/reporters/__init__.py
memray/reporters/_textual_hacks.py
memray/reporters/summary.py
memray/reporters/common.py
memray/reporters/stats.py
memray/reporters/transform.py
memray/reporters/tui.py
memray/reporters/flamegraph.py
memray/reporters/table.py
memray/reporters/tui.css
memray/reporters/tree.css
memray/reporters/templates/classic_base.html
memray/reporters/templates/base.html
memray/reporters/templates/flamegraph.html
memray/reporters/templates/table.html
memray/reporters/templates/__init__.py
memray/reporters/templates/temporal_flamegraph.html
memray/reporters/templates/assets/temporal_flamegraph.js
memray/reporters/templates/assets/flamegraph.css
memray/reporters/templates/assets/table.js
memray/reporters/templates/assets/table.css
memray/reporters/templates/assets/flamegraph.js
memray/reporters/templates/assets/flamegraph_common.js
memray/reporters/templates/assets/vendor/bootstrap.min.css
memray/reporters/templates/assets/vendor/d3-tip.min.js
memray-1.19.1.dist-info/RECORD
memray-1.19.1.dist-info/WHEEL
memray-1.19.1.dist-info/entry_points.txt
memray-1.19.1.dist-info/top_level.txt
memray-1.19.1.dist-info/METADATA
memray-1.19.1.dist-info/licenses/LICENSE
