Metadata-Version: 2.4
Name: memray
Version: 1.19.1
Summary: A memory profiler for Python applications
Home-page: https://github.com/bloomberg/memray
Author: Pablo Galindo Salgado
License: Apache 2.0
Classifier: Intended Audience :: Developers
Classifier: License :: OSI Approved :: Apache Software License
Classifier: Operating System :: POSIX :: Linux
Classifier: Operating System :: MacOS
Classifier: Programming Language :: Python :: 3.7
Classifier: Programming Language :: Python :: 3.8
Classifier: Programming Language :: Python :: 3.9
Classifier: Programming Language :: Python :: 3.10
Classifier: Programming Language :: Python :: 3.11
Classifier: Programming Language :: Python :: 3.12
Classifier: Programming Language :: Python :: 3.13
Classifier: Programming Language :: Python :: 3.14
Classifier: Programming Language :: Python :: Implementation :: CPython
Classifier: Topic :: Software Development :: Debuggers
Requires-Python: >=3.7.0
License-File: LICENSE
Requires-Dist: jinja2>=2.9
Requires-Dist: typing_extensions; python_version < "3.8.0"
Requires-Dist: rich>=11.2.0
Requires-Dist: textual>=0.41.0
Provides-Extra: test
Requires-Dist: Cython; extra == "test"
Requires-Dist: greenlet; python_version < "3.14" and extra == "test"
Requires-Dist: pytest; extra == "test"
Requires-Dist: pytest-cov; extra == "test"
Requires-Dist: ipython; extra == "test"
Requires-Dist: setuptools; extra == "test"
Requires-Dist: pytest-textual-snapshot; extra == "test"
Requires-Dist: textual!=0.65.2,!=0.66,>=0.43; extra == "test"
Requires-Dist: packaging; extra == "test"
Provides-Extra: docs
Requires-Dist: IPython; extra == "docs"
Requires-Dist: bump2version; extra == "docs"
Requires-Dist: sphinx; extra == "docs"
Requires-Dist: furo; extra == "docs"
Requires-Dist: sphinx-argparse; extra == "docs"
Requires-Dist: towncrier; extra == "docs"
Provides-Extra: lint
Requires-Dist: black; extra == "lint"
Requires-Dist: flake8; extra == "lint"
Requires-Dist: isort; extra == "lint"
Requires-Dist: mypy; extra == "lint"
Requires-Dist: check-manifest; extra == "lint"
Provides-Extra: benchmark
Requires-Dist: asv; extra == "benchmark"
Provides-Extra: dev
Requires-Dist: Cython; extra == "dev"
Requires-Dist: greenlet; python_version < "3.14" and extra == "dev"
Requires-Dist: pytest; extra == "dev"
Requires-Dist: pytest-cov; extra == "dev"
Requires-Dist: ipython; extra == "dev"
Requires-Dist: setuptools; extra == "dev"
Requires-Dist: pytest-textual-snapshot; extra == "dev"
Requires-Dist: textual!=0.65.2,!=0.66,>=0.43; extra == "dev"
Requires-Dist: packaging; extra == "dev"
Requires-Dist: black; extra == "dev"
Requires-Dist: flake8; extra == "dev"
Requires-Dist: isort; extra == "dev"
Requires-Dist: mypy; extra == "dev"
Requires-Dist: check-manifest; extra == "dev"
Requires-Dist: IPython; extra == "dev"
Requires-Dist: bump2version; extra == "dev"
Requires-Dist: sphinx; extra == "dev"
Requires-Dist: furo; extra == "dev"
Requires-Dist: sphinx-argparse; extra == "dev"
Requires-Dist: towncrier; extra == "dev"
Requires-Dist: asv; extra == "dev"
Dynamic: author
Dynamic: classifier
Dynamic: description
Dynamic: description-content-type
Dynamic: home-page
Dynamic: license
Dynamic: license-file
Dynamic: provides-extra
Dynamic: requires-dist
Dynamic: requires-python
Dynamic: summary
